sumatra_client/__init__.py
sumatra_client/admin.py
sumatra_client/auth.py
sumatra_client/base.py
sumatra_client/cli.py
sumatra_client/client.py
sumatra_client/config.py
sumatra_client/materialization.py
sumatra_client/model.py
sumatra_client/optimize.py
sumatra_client/table.py
sumatra_client/util.py
sumatra_client/workspace.py
sumatra_client-1.8.0.dist-info/LICENSE
sumatra_client-1.8.0.dist-info/METADATA
sumatra_client-1.8.0.dist-info/WHEEL
sumatra_client-1.8.0.dist-info/entry_points.txt
sumatra_client-1.8.0.dist-info/top_level.txt
sumatra_client-1.8.0.dist-info/RECORD
