Metadata-Version: 2.2
Name: sumatra-client
Version: 1.8.0
Summary: Sumatra Python Client and CLI
Home-page: https://sumatra.ai
Author: Sumatra
Author-email: support@sumatra.ai
License: Sumatra Proprietary
Platform: any
Classifier: Programming Language :: Python :: 3
Classifier: Operating System :: OS Independent
Classifier: License :: Other/Proprietary License
Requires-Python: >=3.9
License-File: LICENSE
Requires-Dist: boto3
Requires-Dist: colorama
Requires-Dist: python_graphql_client
Requires-Dist: pendulum
Requires-Dist: requests
Requires-Dist: click
Requires-Dist: tqdm
Requires-Dist: warrant-lite
Requires-Dist: sumatra-sdk
